ncbimetadata/__init__.py
ncbimetadata/core.py
ncbimetadata-0.1.2.dist-info/LICENSE
ncbimetadata-0.1.2.dist-info/METADATA
ncbimetadata-0.1.2.dist-info/WHEEL
ncbimetadata-0.1.2.dist-info/entry_points.txt
ncbimetadata-0.1.2.dist-info/top_level.txt
ncbimetadata-0.1.2.dist-info/RECORD
