Metadata-Version: 2.1
Name: ncbimetadata
Version: 0.1.2
Summary: ncbimetadata is a package for fast fetching and parsing metadata from ncbi database, and more functionalities are on the way!
Home-page: https://github.com/RyanYuanSun/ncbimetadata
Author: Ryan Alloriadonis
Author-email: yuantai78@gmail.com
License: MIT License
Requires-Python: >3
License-File: LICENSE
Requires-Dist: requests
